MANIFEST.in
README.rst
setup.cfg
setup.py
pci/__init__.py
poplus_pci.egg-info/PKG-INFO
poplus_pci.egg-info/SOURCES.txt
poplus_pci.egg-info/dependency_links.txt
poplus_pci.egg-info/requires.txt
poplus_pci.egg-info/top_level.txt